beamx/__init__.py
beamx/io/__init__.py
beamx/io/filesource.py
beamx/io/aws/__init__.py
beamx/io/aws/glueio.py
beamx/reader/__init__.py
beamx/reader/orc.py
beamx/reader/orc_test.py
beamx/reader/utils.py
beamx/transforms/__init__.py
beamx/transforms/restruct_dict.py
beamx/transforms/restruct_dict_test.py
beamx-0.0.1.dist-info/METADATA
beamx-0.0.1.dist-info/WHEEL
beamx-0.0.1.dist-info/top_level.txt
beamx-0.0.1.dist-info/RECORD
