Metadata-Version: 2.1
Name: beamx
Version: 0.0.1
Summary: A small example package
Home-page: https://github.com/pypa/sampleproject
Author: Arata Furukawa
Author-email: old.river.new@gmail.com
License: UNKNOWN
Platform: UNKNOWN
Classifier: Programming Language :: Python :: 3
Classifier: License :: OSI Approved :: MIT License
Classifier: Operating System :: OS Independent
Requires-Python: >=3.6
Requires-Dist: apache-beam (>=2.22.0)
Requires-Dist: boto3 (>=1.14.15)
Requires-Dist: pyorc (>=0.3.0)
